squad_py/__init__.py
squad_py/example.py
squad_py-0.2.0.dist-info/LICENSE
squad_py-0.2.0.dist-info/METADATA
squad_py-0.2.0.dist-info/WHEEL
squad_py-0.2.0.dist-info/RECORD
