Metadata-Version: 2.1
Name: squad_py
Version: 0.2.0
Summary: Spatial QUality Assessment and Diagnosis
License: MIT
Author: fengsh
Author-email: shaohong.feng.78@gmail.com
Requires-Python: >=3.10,<4.0
Classifier: License :: OSI Approved :: MIT License
Classifier: Programming Language :: Python :: 3
Classifier: Programming Language :: Python :: 3.10
Classifier: Programming Language :: Python :: 3.11
Classifier: Programming Language :: Python :: 3.12
